modelxplain/__init__.py
modelxplain/dashboard.py
modelxplain/explainers.py
modelxplain/model_loader.py
modelxplain/visualization.py
modelxplain-0.1.0.dist-info/LICENSE
modelxplain-0.1.0.dist-info/METADATA
modelxplain-0.1.0.dist-info/WHEEL
modelxplain-0.1.0.dist-info/top_level.txt
modelxplain-0.1.0.dist-info/RECORD
