Metadata-Version: 2.1
Name: modelxplain
Version: 0.1.0
Summary: A package for enhancing model interpretability for machine learning models.
Home-page: https://github.com/yourusername/modelinsightharsh
Author: Your Name
Author-email: your.email@example.com
Classifier: Programming Language :: Python :: 3
Classifier: License :: OSI Approved :: MIT License
Requires-Python: >=3.6
License-File: LICENSE
Requires-Dist: scikit-learn>=0.24.0
Requires-Dist: xgboost>=1.3.0
Requires-Dist: tensorflow>=2.4.0
Requires-Dist: shap>=0.39.0
Requires-Dist: lime>=0.2.0.1
Requires-Dist: eli5>=0.11.0
Requires-Dist: dash>=2.0.0
Requires-Dist: plotly>=5.0.0
Requires-Dist: pandas>=1.1.0
Requires-Dist: numpy>=1.19.0
